[
    {
      "img": "/static/media/pricing-box-img1.03a0b458483a1bc500cf.png",
      "title": "Beginner",
      "price": 120,
      "infos": [
        "0% transaction fee",
        "100 products.",
        "100 funnels",
        "Unlimited landing pages.",
        "Unlimited marketing emails",
        "100,000 contacts",
        "2000 active customers",
        "3 websites",
        "25 admin users"
      ]
    },
    {
      "img": "/static/media/pricing-box-img2.95f6ee63313fb9ddf30a.png",
      "title": "Business",
      "price": 180,
      "infos": [
        "0% transaction fee",
        "100 products.",
        "100 funnels",
        "Unlimited landing pages.",
        "Unlimited marketing emails",
        "100,000 contacts",
        "2000 active customers",
        "3 websites",
        "25 admin users"
      ]
    },
    {
      "img": "/static/media/pricing-box-img3.bfdd1391c854047b7815.png",
      "title": "Professional",
      "price": 200,
      "infos": [
        "0% transaction fee",
        "100 products.",
        "100 funnels",
        "Unlimited landing pages.",
        "Unlimited marketing emails",
        "100,000 contacts",
        "2000 active customers",
        "3 websites",
        "25 admin users"
      ]
    },
    {
      "img": "/static/media/pricing-box-img1.03a0b458483a1bc500cf.png",
      "title": "Beginner",
      "price": 120,
      "infos": [
        "0% transaction fee",
        "100 products.",
        "100 funnels",
        "Unlimited landing pages.",
        "Unlimited marketing emails",
        "100,000 contacts",
        "2000 active customers",
        "3 websites",
        "25 admin users"
      ]
    },
    {
      "img": "/static/media/pricing-box-img2.95f6ee63313fb9ddf30a.png",
      "title": "Beginner",
      "price": 120,
      "infos": [
        "0% transaction fee",
        "100 products.",
        "100 funnels",
        "Unlimited landing pages.",
        "Unlimited marketing emails",
        "100,000 contacts",
        "2000 active customers",
        "3 websites",
        "25 admin users"
      ]
    },
    {
      "img": "/static/media/pricing-box-img3.bfdd1391c854047b7815.png",
      "title": "Beginner",
      "price": 120,
      "infos": [
        "0% transaction fee",
        "100 products.",
        "100 funnels",
        "Unlimited landing pages.",
        "Unlimited marketing emails",
        "100,000 contacts",
        "2000 active customers",
        "3 websites",
        "25 admin users"
      ]
    }
  ]